LICENSE
README.rst
setup.py
sponge/__init__.py
sponge/manager.py
sponge.egg-info/PKG-INFO
sponge.egg-info/SOURCES.txt
sponge.egg-info/dependency_links.txt
sponge.egg-info/requires.txt
sponge.egg-info/top_level.txt
sponge/drivers/__init__.py
sponge/drivers/driver.py
sponge/drivers/memory.py
sponge/drivers/redis.py
sponge/drivers/sqlite.py
tests/__init__.py
tests/driver.py
tests/test_memory.py
tests/test_redis.py
tests/test_sqlite.py